lektor_github_repos.py
lektor_github_repos-0.1.1.dist-info/DESCRIPTION.rst
lektor_github_repos-0.1.1.dist-info/entry_points.txt
lektor_github_repos-0.1.1.dist-info/METADATA
lektor_github_repos-0.1.1.dist-info/metadata.json
lektor_github_repos-0.1.1.dist-info/RECORD
lektor_github_repos-0.1.1.dist-info/top_level.txt
lektor_github_repos-0.1.1.dist-info/WHEEL
