Metadata-Version: 2.0
Name: lektor-github-repos
Version: 0.1.1
Summary: Fetches your GitHub repos for display in Lektor templates
Home-page: https://github.com/marksteve/lektor-github-repos
Author: Mark Steve Samson
Author-email: hello@marksteve.com
License: MIT
Platform: UNKNOWN
Requires-Dist: requests
